{
  "$schema": "http://cyclonedx.org/schema/bom-1.4.schema.json",
  "bomFormat": "CycloneDX",
  "specVersion": "1.4",
  "serialNumber": "urn:uuid:dabd60af-690f-4244-8716-b12deadf0634",
  "version": 1,
  "metadata": {
    "timestamp": "2023-10-11T19:35:51.239437+00:00",
    "tools": [
      {
        "vendor": "CycloneDX",
        "name": "cyclonedx-bom",
        "version": "3.11.2"
      },
      {
        "vendor": "CycloneDX",
        "name": "cyclonedx-python-lib",
        "version": "3.1.5",
        "externalReferences": [
          {
            "url": "https://github.com/CycloneDX/cyclonedx-python-lib/actions",
            "type": "build-system"
          },
          {
            "url": "https://pypi.org/project/cyclonedx-python-lib/",
            "type": "distribution"
          },
          {
            "url": "https://cyclonedx.github.io/cyclonedx-python-lib/",
            "type": "documentation"
          },
          {
            "url": "https://github.com/CycloneDX/cyclonedx-python-lib/issues",
            "type": "issue-tracker"
          },
          {
            "url": "https://github.com/CycloneDX/cyclonedx-python-lib/blob/main/LICENSE",
            "type": "license"
          },
          {
            "url": "https://github.com/CycloneDX/cyclonedx-python-lib/blob/main/CHANGELOG.md",
            "type": "release-notes"
          },
          {
            "url": "https://github.com/CycloneDX/cyclonedx-python-lib",
            "type": "vcs"
          },
          {
            "url": "https://cyclonedx.org",
            "type": "website"
          }
        ]
      }
    ]
  },
  "components": [
    {
      "type": "library",
      "bom-ref": "d7237d02-137e-49f6-90cc-53ff88608082",
      "name": "Faker",
      "version": "19.10.0",
      "purl": "pkg:pypi/faker@19.10.0"
    }
  ],
  "dependencies": [
    {
      "ref": "d7237d02-137e-49f6-90cc-53ff88608082",
      "dependsOn": []
    }
  ]
}
